odoo/addons/mail_check_mailbox_size/README.rst
odoo/addons/mail_check_mailbox_size/__init__.py
odoo/addons/mail_check_mailbox_size/__manifest__.py
odoo/addons/mail_check_mailbox_size/data/cron_data.xml
odoo/addons/mail_check_mailbox_size/i18n/mail_check_mailbox_size.pot
odoo/addons/mail_check_mailbox_size/models/__init__.py
odoo/addons/mail_check_mailbox_size/models/fetchmail.py
odoo/addons/mail_check_mailbox_size/readme/CONFIGURE.rst
odoo/addons/mail_check_mailbox_size/readme/CONTRIBUTORS.rst
odoo/addons/mail_check_mailbox_size/readme/DESCRIPTION.rst
odoo/addons/mail_check_mailbox_size/static/description/icon.png
odoo/addons/mail_check_mailbox_size/static/description/index.html
odoo/addons/mail_check_mailbox_size/views/fetchmail_view.xml
odoo12_addon_mail_check_mailbox_size-12.0.1.0.0.99.dev4.dist-info/METADATA
odoo12_addon_mail_check_mailbox_size-12.0.1.0.0.99.dev4.dist-info/WHEEL
odoo12_addon_mail_check_mailbox_size-12.0.1.0.0.99.dev4.dist-info/top_level.txt
odoo12_addon_mail_check_mailbox_size-12.0.1.0.0.99.dev4.dist-info/RECORD
